bionompy/__init__.py
bionompy/package_metadata.py
bionompy/bionompy/__init__.py
bionompy/bionompy/agent.py
bionompy/bionompy/occurrence.py
bionompy/bionompy/parse.py
bionompy/bionompy/person.py
bionompy/bionompy/suggest.py
bionompy/utils/__init__.py
bionompy/utils/bionompy_utils.py
test/__init__.py
test/test-agent.py
test/test-occurrences.py
test/test-parse.py
test/test-person.py
test/test-suggest.py
bionompy-0.0.1.dist-info/LICENSE.txt
bionompy-0.0.1.dist-info/METADATA
bionompy-0.0.1.dist-info/WHEEL
bionompy-0.0.1.dist-info/top_level.txt
bionompy-0.0.1.dist-info/RECORD
