Metadata-Version: 2.1
Name: bionompy
Version: 0.0.1
Summary: Python client for Bionomia
Home-page: http://github.com/speciesfilegroup/bionompy
Download-URL: https://github.com/speciesfilegroup/bionompy/archive/refs/tags/v0.0.1.tar.gz
Author: Geoff Ower
Author-email: gdower@illinois.edu
License: NCSA
Keywords: bionomia,biodiversity,collectors,specimens,API,web-services,species,natural history,taxonomists,biologists
Classifier: Development Status :: 5 - Production/Stable
Classifier: Intended Audience :: Science/Research
Classifier: Topic :: Scientific/Engineering :: Bio-Informatics
Classifier: Natural Language :: English
Classifier: License :: OSI Approved :: University of Illinois/NCSA Open Source License
Classifier: Programming Language :: Python
Classifier: Programming Language :: Python :: 3.9
Classifier: Programming Language :: Python :: 3.10
Classifier: Programming Language :: Python :: 3.11
License-File: LICENSE.txt
Requires-Dist: requests >2.7
Requires-Dist: beautifulsoup4 >4.9.0
Requires-Dist: lxml >4.4.3
Provides-Extra: dev
Requires-Dist: codecov ; extra == 'dev'
Requires-Dist: pytest ; extra == 'dev'
Requires-Dist: pytest-cov ; extra == 'dev'
Requires-Dist: sphinx >7.2.0 ; extra == 'dev'
Requires-Dist: sphinx-issues ; extra == 'dev'
Requires-Dist: sphinx-rtd-theme ; extra == 'dev'
Requires-Dist: twine ; extra == 'dev'
Requires-Dist: wheel ; extra == 'dev'
